r2g2/__init__.py
r2g2/anvio.py
r2g2/config.py
r2g2/core.py
r2g2/dependency_generator.py
r2g2/recursive.py
r2g2/templates.py
r2g2/utils.py
r2g2/xml_generators.py
r2g2/parsers/FakeArg.r
r2g2/parsers/__init__.py
r2g2/parsers/r_parser.py
r2g2/scripts/__init__.py
r2g2/scripts/r2g2_package.py
r2g2/scripts/r2g2_script.py
r2g2-0.1.1.dist-info/licenses/LICENSE
r2g2-0.1.1.dist-info/METADATA
r2g2-0.1.1.dist-info/WHEEL
r2g2-0.1.1.dist-info/entry_points.txt
r2g2-0.1.1.dist-info/top_level.txt
r2g2-0.1.1.dist-info/RECORD
