Metadata-Version: 2.4
Name: r2g2
Version: 0.1.1
Summary: A tool to convert R scripts and packages to Galaxy wrappers
Home-page: https://github.com/BlankenbergLab/r2g2
Author: Jayadev Joshi, Fabio Cumbo, Daniel Blankenberg
License: MIT
Classifier: Programming Language :: Python :: 3
Classifier: License :: OSI Approved :: MIT License
Classifier: Operating System :: OS Independent
Requires-Python: >=3.6
License-File: LICENSE
Requires-Dist: rpy2>=3.6.1
Requires-Dist: jinja2
Requires-Dist: requests
Requires-Dist: packaging
Dynamic: author
Dynamic: classifier
Dynamic: description
Dynamic: description-content-type
Dynamic: home-page
Dynamic: license
Dynamic: license-file
Dynamic: requires-dist
Dynamic: requires-python
Dynamic: summary
